FPU/FPMul.v
//`include "shift/shift.v"
//`include "addsub/addsub.v"
//`include "mul/mul.v"

module FPMul (
    input  [63:0] N1,
    input  [63:0] N2,
    output [63:0] out
);

  // Extracting Sign, Exponent, Mantissa
  wire [51:0] M_1;
  wire [51:0] M_2;
  wire [10:0] E_1;
  wire [10:0] E_2;
  wire S_1;
  wire S_2;
  assign M_1 = N1[51:0];
  assign M_2 = N2[51:0];

  assign E_1 = N1[62:52];
  assign E_2 = N2[62:52];

  assign S_1 = N1[63];
  assign S_2 = N2[63];


  wire [63:0] temp1;
  wire [63:0] temp2;
  assign temp1 = {12'b1, M_1};
  assign temp2 = {12'b1, M_2};


  // Adding exponnts E_1, E_2
  wire [63:0] exponent_1 = {53'b0, E_1} + {53'b0, E_2};
  wire cout1;
  wire cout2;
  wire [63:0] exponent_2 = exponent_1 - 64'd1023;

  /*
  addsub FPmul_exponent_sum (
      .a({53'b0, E_1}),
      .b({53'b0, E_2}),
      .sel(1'b0),
      .res(exponent_1),
      .cout(cout1)
  );
  */
  // Then subtracting bias
  /*
  addsub FPmul_exponent_bias (
      .a({exponent_1}),
      .b({64'd1023}),
      .sel(1'b1),
      .res(exponent_2),
      .cout(cout2)
  );
  */


  // Multiplying mantissas M_1 and M_2
  wire [127:0] mantissa_product = {64'b0, 12'b1, M_1} * {64'b0, 12'b1, M_2};
  /*
  mul FPmul_mantissa (
      .a({12'b1, M_1}),
      .b({12'b1, M_2}),
      .sign(1'b0),
      .res(mantissa_product)
  );
  */
  // Normalizing mantissa
  wire [52:0] mantissa_normalized;
  wire L;
  wire G;
  wire R;
  wire S;
  wire round;

  // Also setting LSB, Guard, Round, Sticky bits
  assign mantissa_normalized = (mantissa_product[105])?mantissa_product[105:53]:mantissa_product[104:52];
  assign L = (mantissa_product[105]) ? mantissa_product[53] : mantissa_product[52];
  assign G = (mantissa_product[105]) ? mantissa_product[52] : mantissa_product[51];
  assign R = (mantissa_product[105]) ? mantissa_product[51] : mantissa_product[50];
  assign S = (mantissa_product[105]) ? |mantissa_product[50:0] : |mantissa_product[49:0];

  // Updating exponent (if needed) after normalizing
  wire [63:0] exponent_3 = exponent_2 + (mantissa_product[105] ? 64'b1 : 64'b0);
  wire cout3;
  /*
  addsub FPmul_exponent_norm (
      .a(exponent_2),
      .b(mantissa_product[105] ? 64'b1 : 64'b0),
      .sel(1'b0),
      .res(exponent_3),
      .cout(cout3)
  );
  */

  assign round = (G & (R | S)) | (L & G & (~R) & (~S));
  wire [64:0] mantissa_rounded_cout = {12'b0, mantissa_normalized} + (round ? 65'b1 : 65'b0);
  wire [63:0] mantissa_rounded = mantissa_rounded_cout[63:0];
  wire cout = mantissa_rounded_cout[64];
  /*
  addsub FPmul_round (
      .a({11'b0, mantissa_normalized}),
      .b((round) ? {63'b0, 1'b1} : {63'b0, 1'b0}),
      .sel(1'b0),
      .cout(cout),
      .res(mantissa_rounded)
  );
  */

  wire [51:0] mantissa_renormalized;
  wire [63:0] exponent_4 = exponent_3 + ((cout) ? 64'b1 : 64'b0);
  wire cout4;

  /*
  addsub FPmul_exponent_renorm (
      .a(exponent_3),
      .b((cout) ? 64'b1 : 64'b0),
      .sel(1'b0),
      .res(exponent_4),
      .cout(cout4)
  );*/

  assign mantissa_renormalized = (cout) ? mantissa_rounded[52:1] : mantissa_rounded[51:0];
  assign out[51:0] = mantissa_renormalized;
  assign out[62:52] = exponent_4[10:0];
  assign out[63] = S_1 ^ S_2;

endmodule

FPU/FP_Mul/test.v

`timescale 1ns / 1ps

module FPMul_tb;

  reg [63:0] N1;
  reg [63:0] N2;
  wire [63:0] out;
  wire [63:0] temp1;
  wire [63:0] temp2;
  wire [127:0] mantissa_product;
  wire [52:0] mantissa_normalized;
  wire [52:0] mantissa_renormalized;
  wire [52:0] mantissa_rounded;
  wire round;
  FPMul uut (
      .N1 (N1),
      .N2 (N2),
      .out(out)
  );
  assign temp1 = uut.temp1;
  assign temp2 = uut.temp2;
  assign mantissa_product = uut.mantissa_product;
  assign mantissa_normalized = uut.mantissa_normalized;
  assign mantissa_renormalized = uut.mantissa_renormalized;
  assign mantissa_rounded = uut.mantissa_rounded;
  assign round = uut.round;
  initial begin
    $dumpvars(0, FPMul_tb);

    // Test 1: 2.0 * 3.0
    N1 = 64'h4000000000000000;  // 2.0
    N2 = 64'h4008000000000000;  // 3.0
    #10;
    $display("Test 1: 2.0 * 3.0, Output: %h", out);
    //$display("temp1: %h", temp1);
    //$display("temp2: %h", temp2);
    //$display("Mantissa Product: %h", mantissa_product);
    //$display("Mantissa Normlized: %h", mantissa_normalized);
    //$display("Mantissa Rounded: %h", mantissa_rounded);
    //$display("Round or not: %h", round);
    //$display("Mantissa REnormalized: %h", mantissa_renormalized);


    // Test 2: 0.0 * 123.0
    N1 = 64'h0000000000000000;  // 0.0
    N2 = 64'h405ec00000000000;  // 123.0
    #10;
    $display("Test 2: 0.0 * 123.0, Output: %h", out);
    //$display("temp1: %h", temp1);
    //$display("temp2: %h", temp2);
    //$display("Mantissa Product: %h", mantissa_product);


    // Test 3: 1.5 * 5.0
    N1 = 64'h3ff8000000000000;  // 1.5
    N2 = 64'h4014000000000000;  // 5.0
    #10;
    $display("Test 3: 1.5 * 5.0, Output: %h", out);
    //$display("temp1: %h", temp1);
    //$display("temp2: %h", temp2);
    //$display("Mantissa Product: %h", mantissa_product);


    // Test 4: -2.0 * 3.0
    N1 = 64'hc000000000000000;  // -2.0
    N2 = 64'h4008000000000000;  // 3.0
    #10;
    $display("Test 4: -2.0 * 3.0, Output: %h", out);
    //$display("temp1: %h", temp1);
    //$display("temp2: %h", temp2);
    //$display("Mantissa Product: %h", mantissa_product);


    // Test 5: 0.0 * 0.0
    N1 = 64'h0000000000000000;  // 0.0
    N2 = 64'h0000000000000000;  // 0.0
    #10;
    $display("Test 5: 0.0 * 0.0, Output: %h", out);

    // Test 6: 1.0 * 1.0
    N1 = 64'h3ff0000000000000;  // 1.0
    N2 = 64'h3ff0000000000000;  // 1.0
    #10;
    $display("Test 6: 1.0 * 1.0, Output: %h", out);

    // Test 7: 10.0 * 0.1
    N1 = 64'h4024000000000000;  // 10.0
    N2 = 64'h3fb999999999999a;  // 0.1
    #10;
    $display("Test 7: 10.0 * 0.1, Output: %h", out);

    // Test 8: -5.0 * -5.0
    N1 = 64'hc014000000000000;  // -5.0
    N2 = 64'hc014000000000000;  // -5.0
    #10;
    $display("Test 8: -5.0 * -5.0, Output: %h", out);


    $finish;
  end
endmodule

FPU/FSQRT/FP_Mul/dump.vcd
$date
	Mon Oct 27 23:24:11 2025
$end
$version
	Icarus Verilog
$end
$timescale
	1ps
$end
$scope module FPMul_tb $end
$var wire 53 ! mantissa_normalized [52:0] $end
$var wire 128 " mantissa_product [127:0] $end
$var wire 1 # round $end
$var wire 64 $ temp1 [63:0] $end
$var wire 64 % temp2 [63:0] $end
$var wire 64 & out [63:0] $end
$var wire 53 ' mantissa_rounded [52:0] $end
$var wire 53 ( mantissa_renormalized [52:0] $end
$var reg 64 ) N1 [63:0] $end
$var reg 64 * N2 [63:0] $end
$scope module uut $end
$var wire 64 + N1 [63:0] $end
$var wire 64 , N2 [63:0] $end
$var wire 1 - round $end
$var wire 64 . temp2 [63:0] $end
$var wire 64 / temp1 [63:0] $end
$var wire 64 0 out [63:0] $end
$var wire 65 1 mantissa_rounded_cout [64:0] $end
$var wire 64 2 mantissa_rounded [63:0] $end
$var wire 52 3 mantissa_renormalized [51:0] $end
$var wire 128 4 mantissa_product [127:0] $end
$var wire 53 5 mantissa_normalized [52:0] $end
$var wire 64 6 exponent_4 [63:0] $end
$var wire 64 7 exponent_3 [63:0] $end
$var wire 64 8 exponent_2 [63:0] $end
$var wire 64 9 exponent_1 [63:0] $end
$var wire 1 : cout $end
$var wire 1 ; S_2 $end
$var wire 1 < S_1 $end
$var wire 1 = S $end
$var wire 1 > R $end
$var wire 52 ? M_2 [51:0] $end
$var wire 52 @ M_1 [51:0] $end
$var wire 1 A L $end
$var wire 1 B G $end
$var wire 11 C E_2 [10:0] $end
$var wire 11 D E_1 [10:0] $end
$upscope $end
$upscope $end
$enddefinitions $end
$comment Show the parameter values. $end
$dumpall
$end
#0
$dumpvars
b10000000000 D
b10000000000 C
0B
0A
b0 @
b1000000000000000000000000000000000000000000000000000 ?
0>
0=
0<
0;
0:
b100000000000 9
b10000000001 8
b10000000001 7
b10000000001 6
b11000000000000000000000000000000000000000000000000000 5
b110000000000000000000000000000000000000000000000000000000000000000000000000000000000000000000000000000000 4
b1000000000000000000000000000000000000000000000000000 3
b11000000000000000000000000000000000000000000000000000 2
b11000000000000000000000000000000000000000000000000000 1
b100000000011000000000000000000000000000000000000000000000000000 0
b10000000000000000000000000000000000000000000000000000 /
b11000000000000000000000000000000000000000000000000000 .
0-
b100000000001000000000000000000000000000000000000000000000000000 ,
b100000000000000000000000000000000000000000000000000000000000000 +
b100000000001000000000000000000000000000000000000000000000000000 *
b100000000000000000000000000000000000000000000000000000000000000 )
b1000000000000000000000000000000000000000000000000000 (
b11000000000000000000000000000000000000000000000000000 '
b100000000011000000000000000000000000000000000000000000000000000 &
b11000000000000000000000000000000000000000000000000000 %
b10000000000000000000000000000000000000000000000000000 $
0#
b110000000000000000000000000000000000000000000000000000000000000000000000000000000000000000000000000000000 "
b11000000000000000000000000000000000000000000000000000 !
$end
#10000
b1110110000000000000000000000000000000000000000000000 (
b1110110000000000000000000000000000000000000000000000 3
b11110110000000000000000000000000000000000000000000000 '
b11110110000000000000000000000000000000000000000000000 2
b11110110000000000000000000000000000000000000000000000 1
b11110110000000000000000000000000000000000000000000000 !
b11110110000000000000000000000000000000000000000000000 5
b1101110110000000000000000000000000000000000000000000000 &
b1101110110000000000000000000000000000000000000000000000 0
b11110110000000000000000000000000000000000000000000000 %
b11110110000000000000000000000000000000000000000000000 .
b111101100000000000000000000000000000000000000000000000000000000000000000000000000000000000000000000000000 "
b111101100000000000000000000000000000000000000000000000000000000000000000000000000000000000000000000000000 4
b1110110000000000000000000000000000000000000000000000 ?
b10000000101 C
b110 6
b110 7
b110 8
b10000000101 9
b0 D
b100000001011110110000000000000000000000000000000000000000000000 *
b100000001011110110000000000000000000000000000000000000000000000 ,
b0 )
b0 +
#20000
b1110000000000000000000000000000000000000000000000000 (
b1110000000000000000000000000000000000000000000000000 3
b11110000000000000000000000000000000000000000000000000 '
b11110000000000000000000000000000000000000000000000000 2
b11110000000000000000000000000000000000000000000000000 1
b11110000000000000000000000000000000000000000000000000 !
b11110000000000000000000000000000000000000000000000000 5
b100000000011110000000000000000000000000000000000000000000000000 &
b100000000011110000000000000000000000000000000000000000000000000 0
b10100000000000000000000000000000000000000000000000000 %
b10100000000000000000000000000000000000000000000000000 .
b100000000000000000000000000000000000000000000000000 ?
b10000000001 C
b11000000000000000000000000000000000000000000000000000 $
b11000000000000000000000000000000000000000000000000000 /
b111100000000000000000000000000000000000000000000000000000000000000000000000000000000000000000000000000000 "
b111100000000000000000000000000000000000000000000000000000000000000000000000000000000000000000000000000000 4
b1000000000000000000000000000000000000000000000000000 @
b10000000001 6
b10000000001 7
b10000000001 8
b100000000000 9
b1111111111 D
b100000000010100000000000000000000000000000000000000000000000000 *
b100000000010100000000000000000000000000000000000000000000000000 ,
b11111111111000000000000000000000000000000000000000000000000000 )
b11111111111000000000000000000000000000000000000000000000000000 +
#30000
b1000000000000000000000000000000000000000000000000000 (
b1000000000000000000000000000000000000000000000000000 3
b11000000000000000000000000000000000000000000000000000 '
b11000000000000000000000000000000000000000000000000000 2
b11000000000000000000000000000000000000000000000000000 1
b11000000000000000000000000000000000000000000000000000 !
b11000000000000000000000000000000000000000000000000000 5
b1100000000011000000000000000000000000000000000000000000000000000 &
b1100000000011000000000000000000000000000000000000000000000000000 0
b11000000000000000000000000000000000000000000000000000 %
b11000000000000000000000000000000000000000000000000000 .
b1000000000000000000000000000000000000000000000000000 ?
b10000000000 C
b10000000000000000000000000000000000000000000000000000 $
b10000000000000000000000000000000000000000000000000000 /
b110000000000000000000000000000000000000000000000000000000000000000000000000000000000000000000000000000000 "
b110000000000000000000000000000000000000000000000000000000000000000000000000000000000000000000000000000000 4
b0 @
b10000000001 6
b10000000001 7
b10000000001 8
b100000000000 9
b10000000000 D
1<
b100000000001000000000000000000000000000000000000000000000000000 *
b100000000001000000000000000000000000000000000000000000000000000 ,
b1100000000000000000000000000000000000000000000000000000000000000 )
b1100000000000000000000000000000000000000000000000000000000000000 +
#40000
b0 (
b0 3
b10000000000000000000000000000000000000000000000000000 '
b10000000000000000000000000000000000000000000000000000 2
b10000000000000000000000000000000000000000000000000000 1
b10000000000000000000000000000000000000000000000000000 !
b10000000000000000000000000000000000000000000000000000 5
b100000000010000000000000000000000000000000000000000000000000000 &
b100000000010000000000000000000000000000000000000000000000000000 0
b10000000000000000000000000000000000000000000000000000 %
b10000000000000000000000000000000000000000000000000000 .
b100000000000000000000000000000000000000000000000000000000000000000000000000000000000000000000000000000000 "
b100000000000000000000000000000000000000000000000000000000000000000000000000000000000000000000000000000000 4
b0 ?
b0 C
b1111111111111111111111111111111111111111111111111111110000000001 6
b1111111111111111111111111111111111111111111111111111110000000001 7
b1111111111111111111111111111111111111111111111111111110000000001 8
b0 9
b0 D
0<
b0 *
b0 ,
b0 )
b0 +
#50000
b11111111110000000000000000000000000000000000000000000000000000 &
b11111111110000000000000000000000000000000000000000000000000000 0
b1111111111 C
b1111111111 6
b1111111111 7
b1111111111 8
b11111111110 9
b1111111111 D
b11111111110000000000000000000000000000000000000000000000000000 *
b11111111110000000000000000000000000000000000000000000000000000 ,
b11111111110000000000000000000000000000000000000000000000000000 )
b11111111110000000000000000000000000000000000000000000000000000 +
#60000
1>
b11111111110000000000000000000000000000000000000000000000000000 &
b11111111110000000000000000000000000000000000000000000000000000 0
b11001100110011001100110011001100110011001100110011010 %
b11001100110011001100110011001100110011001100110011010 .
b1001100110011001100110011001100110011001100110011010 ?
b1111111011 C
b10100000000000000000000000000000000000000000000000000 $
b10100000000000000000000000000000000000000000000000000 /
b1000000000000000000000000000000000000000000000000000001000000000000000000000000000000000000000000000000000 "
b1000000000000000000000000000000000000000000000000000001000000000000000000000000000000000000000000000000000 4
b100000000000000000000000000000000000000000000000000 @
b1111111111 6
b1111111111 7
b1111111110 8
b11111111101 9
b10000000010 D
b11111110111001100110011001100110011001100110011001100110011010 *
b11111110111001100110011001100110011001100110011001100110011010 ,
b100000000100100000000000000000000000000000000000000000000000000 )
b100000000100100000000000000000000000000000000000000000000000000 +
#70000
b1001000000000000000000000000000000000000000000000000 (
b1001000000000000000000000000000000000000000000000000 3
b11001000000000000000000000000000000000000000000000000 '
b11001000000000000000000000000000000000000000000000000 2
b11001000000000000000000000000000000000000000000000000 1
b11001000000000000000000000000000000000000000000000000 !
b11001000000000000000000000000000000000000000000000000 5
0>
b100000000111001000000000000000000000000000000000000000000000000 &
b100000000111001000000000000000000000000000000000000000000000000 0
b10100000000000000000000000000000000000000000000000000 %
b10100000000000000000000000000000000000000000000000000 .
b110010000000000000000000000000000000000000000000000000000000000000000000000000000000000000000000000000000 "
b110010000000000000000000000000000000000000000000000000000000000000000000000000000000000000000000000000000 4
b100000000000000000000000000000000000000000000000000 ?
b10000000001 C
1;
b10000000011 6
b10000000011 7
b10000000011 8
b100000000010 9
b10000000001 D
1<
b1100000000010100000000000000000000000000000000000000000000000000 *
b1100000000010100000000000000000000000000000000000000000000000000 ,
b1100000000010100000000000000000000000000000000000000000000000000 )
b1100000000010100000000000000000000000000000000000000000000000000 +
