FPU/FSQRT/FP_Adder/shift_amount.v
module shift_amount (
    input [53:0] A,
    input add,
    output [6:0] shift_amount
);
  // For the case of Adddition
  wire [6:0] shift_amount_2 = (A[53]) ? 7'd1 : 7'd0;

  // For the case of Subtraction
  // Finding leading 1
  wire [6:0] shift_amount_1 = (A[52]) ? 7'd0 :
                       (A[51]) ? 7'd1 :
                       (A[50]) ? 7'd2 :
                       (A[49]) ? 7'd3 :
                       (A[48]) ? 7'd4 :
                       (A[47]) ? 7'd5 :
                       (A[46]) ? 7'd6 :
                       (A[45]) ? 7'd7 :
                       (A[44]) ? 7'd8 :
                       (A[43]) ? 7'd9 :
                       (A[42]) ? 7'd10 :
                       (A[41]) ? 7'd11 :
                       (A[40]) ? 7'd12 :
                       (A[39]) ? 7'd13 :
                       (A[38]) ? 7'd14 :
                       (A[37]) ? 7'd15 :
                       (A[36]) ? 7'd16 :
                       (A[35]) ? 7'd17 :
                       (A[34]) ? 7'd18 :
                       (A[33]) ? 7'd19 :
                       (A[32]) ? 7'd20 :
                       (A[31]) ? 7'd21 :
                       (A[30]) ? 7'd22 :
                       (A[29]) ? 7'd23 :
                       (A[28]) ? 7'd24 :
                       (A[27]) ? 7'd25 :
                       (A[26]) ? 7'd26 :
                       (A[25]) ? 7'd27 :
                       (A[24]) ? 7'd28 :
                       (A[23]) ? 7'd29 :
                       (A[22]) ? 7'd30 :
                       (A[21]) ? 7'd31 :
                       (A[20]) ? 7'd32 :
                       (A[19]) ? 7'd33 :
                       (A[18]) ? 7'd34 :
                       (A[17]) ? 7'd35 :
                       (A[16]) ? 7'd36 :
                       (A[15]) ? 7'd37 :
                       (A[14]) ? 7'd38 :
                       (A[13]) ? 7'd39 :
                       (A[12]) ? 7'd40 :
                       (A[11]) ? 7'd41 :
                       (A[10]) ? 7'd42 :
                       (A[9])  ? 7'd43 :
                       (A[8])  ? 7'd44 :
                       (A[7])  ? 7'd45 :
                       (A[6])  ? 7'd46 :
                       (A[5])  ? 7'd47 :
                       (A[4])  ? 7'd48 :
                       (A[3])  ? 7'd49 :
                       (A[2])  ? 7'd50 :
                       (A[1])  ? 7'd51 :
                       (A[0])  ? 7'd52 : 11'd53;

  // Accordingly setting shift amount
  assign shift_amount = (add) ? shift_amount_2 : shift_amount_1;
endmodule

FPU/FP_Sub/FPAdder.v
`include "shift_amount.v"
module FPAdder (
    input  [63:0] A,
    input  [63:0] B,
    output [63:0] out
);

  // Extracting Sign, Exponent, Mantissa
  wire [51:0] M_A;
  wire [51:0] M_B;
  wire [10:0] E_A;
  wire [10:0] E_B;
  wire S_A;
  wire S_B;
  assign M_A = A[51:0];
  assign M_B = B[51:0];

  assign E_A = A[62:52];
  assign E_B = B[62:52];

  assign S_A = A[63];
  assign S_B = B[63];

  // Shifting smaller number

  // Setting control bit
  wire cntrl = (E_A < E_B);
  // Amount to shift smaller number by
  wire [10:0] shift_amt = (cntrl) ? (E_B - E_A) : (E_A - E_B);


  // Setting M_1, M_2 as operands of Add/Sub unit
  wire [51:0] M = (cntrl) ? M_A : M_B;
  wire [51:0] M2 = (~cntrl) ? M_A : M_B;
  wire [10:0] exp_1 = (cntrl) ? E_B : E_A;

  wire [52:0] M_1 = M1 >> shift_amt;
  wire [52:0] M1 = {1'b1, M};
  wire [52:0] M_2 = {1'b1, M2};


  // Performing addition/subtraction
  wire add = ~(S_A ^ S_B);
  wire [53:0] temp_mantissa = ~add ? ({1'b0, M_2} - {1'b0, M_1}) : ({1'b0, M_2} + {1'b0, M_1});

  // Setting sign bit
  wire zer0;
  assign zer0 = ~|temp_mantissa;
  wire temp1 = (~(S_A ^ S_B) & (S_A & S_B));
  wire temp2 = ((S_A ^ S_B) & (((~cntrl) & S_A) | (cntrl & S_B)));
  assign out[63] = zer0 ? 0 : temp1 | temp2;

  // Normalizing mantissa
  wire [6:0] shift_amt_1;
  shift_amount shift_amont (
      .A(temp_mantissa),
      .add(add),
      .shift_amount(shift_amt_1)
  );

  wire [53:0] sub_shift = temp_mantissa << shift_amt_1;
  wire [53:0] add_shift = temp_mantissa >> shift_amt_1;
  wire [52:0] shifted_mantissa = (add) ? (add_shift[52:0]) : (sub_shift[52:0]);
  wire [52:0] shifted_temp_mantissa;

  // Updating exponent based on mantissa shift
  wire [11:0] add_exp = exp_1 + ((temp_mantissa[53]) ? 11'b1 : 11'b0);
  wire [11:0] sub_exp = exp_1 - (shift_amt_1);
  wire [10:0] exp_2 = add ? add_exp : sub_exp;

  // Rounding and renormalizing (updating exponent accordingly)
  wire [53:0] rounded_mantissa_cout = shifted_mantissa + {52'b0, temp_mantissa[0] & temp_mantissa[1]};
  wire [52:0] rounded_mantissa = rounded_mantissa_cout[52:0];
  wire cout = rounded_mantissa_cout[53];
  wire [10:0] exp_rnorm = exp_2 + (cout ? 11'b1 : 11'b0);

  // Findal values of mantissa and exponent
  assign out[62:52] = zer0 ? 11'b0 : exp_rnorm;
  assign out[51:0]  = cout ? rounded_mantissa[52:1] : rounded_mantissa[51:0];


endmodule

FPU/FP_Sub/FPSub.v
`include "FPAdder.v"
module FPSub (
    input  [63:0] A,
    input  [63:0] B,
    output [63:0] out
);
  FPAdder FP_subtraction (
      .A  (A),
      .B  (B ^ 64'h8000000000000000),
      .out(out)
  );
endmodule

FPU/FP_Sub/test.v
`timescale 1ns / 1ps

module FPAdder_tb;

  reg [63:0] A;
  reg [63:0] B;
  wire [63:0] out;

  // Internal temporary variables within FPAdder for observation
  wire [52:0] M_1;
  wire [52:0] M_2;
  wire [10:0] shift_amt;
  wire [10:0] E_A;
  wire [10:0] E_B;
  wire cout;
  wire [53:0] temp_mantissa;


  wire addorsub;
  // Instantiate the FPAdder
  FPSub uut (
      .A  (A),
      .B  (B),
      .out(out)
  );

  // Hierarchical references to internal nets (depends on your simulator)
  /*
  assign M_1 = uut.M_1;
  assign M_2 = uut.M_2;
  assign shift_amt = uut.shift_amt;
  assign addorsub = uut.S_A ^ uut.S_B;
  assign E_A = uut.E_A;
  assign E_B = uut.E_B;
  assign cout = uut.cout;
  assign temp_mantissa = uut.temp_mantissa;
  wire [6:0] shift_amt_1 = uut.shift_amt_1;
  wire add = uut.add;
  wire [52:0] shifted_mantissa = uut.shifted_mantissa;
  */

  initial begin
    $dumpvars(0, FPAdder_tb);

    // Test case 1: simple numbers
    A = 64'h4043800000000000;  // 39.0
    B = 64'h4024000000000000;  // 10.0
    #10;
    $display("Test 1: 39.0 - 10.0");
    $display("Result: %h", out);

    // Test case 2: positive and negative
    A = 64'h402e000000000000;  // 15.0
    B = 64'hc014000000000000;  // -5.0
    #10;
    $display("Test 2: 15.0 - (-5.0)");
    $display("Result: %h", out);

    // Test case 3: positive and negative, larger negative
    A = 64'h4014000000000000;  // 5.0
    B = 64'hc02e000000000000;  // -15.0
    #10;
    $display("Test 3: 5.0 - (-15.0)");
    $display("Result: %h", out);


    // Test case 4: both negative
    A = 64'hc024000000000000;  // -10.0
    B = 64'hc014000000000000;  // -5.0
    #10;
    $display("Test 4: -10.0 - (-5.0)");
    $display("Result: %h", out);

    // Test case 5: zero and positive
    A = 64'h0000000000000000;  // 0.0
    B = 64'h3ff0000000000000;  // 1.0
    #10;
    $display("Test 5: 0.0 - 1.0");
    $display("Result: %h", out);

    // Test case 6: zero and negative
    A = 64'h0000000000000000;  // 0.0
    B = 64'hbff0000000000000;  // -1.0
    #10;
    $display("Test 6: 0.0 - (-1.0)");
    $display("Result: %h", out);

    // Test case 7: large and small positive
    A = 64'h408f400000000000;  // 1000.0
    B = 64'h3f847ae147ae147b;  // 0.01
    #10;
    $display("Test 7: 1000.0 - 0.01");
    $display("Result: %h", out);

    // Test case 8: large positive and large negative
    A = 64'h408f400000000000;  // 1000.0
    B = 64'hc08f400000000000;  // -1000.0
    #10;
    $display("Test 8: 1000.0 - (-1000.0)");
    $display("Result: %h", out);

    // Test case 9: small positive and small negative
    A = 64'h3f847ae147ae147b;  // 0.01
    B = 64'hbf847ae147ae147b;  // -0.01
    #10;
    $display("Test 9: 0.01 - (-0.01)");
    $display("Result: %h", out);

    // Test case 10: small positive and small negative
    A = 64'h4004000000000000;  // 2.5
    B = 64'h400c000000000000;  // 3.5
    #10;
    $display("Test 9: 2.5 - 3.5");
    $display("Result: %h", out);


    $finish;
  end


endmodule

FPU/FP_Sub/dump.vcd
$date
	Mon Oct 27 23:59:45 2025
$end
$version
	Icarus Verilog
$end
$timescale
	1ps
$end
$scope module FPAdder_tb $end
$var wire 64 ! out [63:0] $end
$var reg 64 " A [63:0] $end
$var reg 64 # B [63:0] $end
$scope module uut $end
$var wire 64 $ A [63:0] $end
$var wire 64 % B [63:0] $end
$var wire 64 & out [63:0] $end
$scope module FP_subtraction $end
$var wire 64 ' A [63:0] $end
$var wire 64 ( B [63:0] $end
$var wire 1 ) add $end
$var wire 1 * temp1 $end
$var wire 1 + temp2 $end
$var wire 1 , zer0 $end
$var wire 54 - temp_mantissa [53:0] $end
$var wire 54 . sub_shift [53:0] $end
$var wire 12 / sub_exp [11:0] $end
$var wire 53 0 shifted_mantissa [52:0] $end
$var wire 7 1 shift_amt_1 [6:0] $end
$var wire 11 2 shift_amt [10:0] $end
$var wire 54 3 rounded_mantissa_cout [53:0] $end
$var wire 53 4 rounded_mantissa [52:0] $end
$var wire 64 5 out [63:0] $end
$var wire 11 6 exp_rnorm [10:0] $end
$var wire 11 7 exp_2 [10:0] $end
$var wire 11 8 exp_1 [10:0] $end
$var wire 1 9 cout $end
$var wire 1 : cntrl $end
$var wire 54 ; add_shift [53:0] $end
$var wire 12 < add_exp [11:0] $end
$var wire 1 = S_B $end
$var wire 1 > S_A $end
$var wire 52 ? M_B [51:0] $end
$var wire 52 @ M_A [51:0] $end
$var wire 53 A M_2 [52:0] $end
$var wire 53 B M_1 [52:0] $end
$var wire 52 C M2 [51:0] $end
$var wire 53 D M1 [52:0] $end
$var wire 52 E M [51:0] $end
$var wire 11 F E_B [10:0] $end
$var wire 11 G E_A [10:0] $end
$scope module shift_amont $end
$var wire 54 H A [53:0] $end
$var wire 1 ) add $end
$var wire 7 I shift_amount_2 [6:0] $end
$var wire 7 J shift_amount_1 [6:0] $end
$var wire 7 K shift_amount [6:0] $end
$upscope $end
$upscope $end
$upscope $end
$upscope $end
$enddefinitions $end
$comment Show the parameter values. $end
$dumpall
$end
#0
$dumpvars
b1 K
b1 J
b0 I
b1110100000000000000000000000000000000000000000000000 H
b10000000100 G
b10000000010 F
b100000000000000000000000000000000000000000000000000 E
b10100000000000000000000000000000000000000000000000000 D
b11100000000000000000000000000000000000000000000000 C
b101000000000000000000000000000000000000000000000000 B
b10011100000000000000000000000000000000000000000000000 A
b11100000000000000000000000000000000000000000000000 @
b100000000000000000000000000000000000000000000000000 ?
0>
1=
b10000000100 <
b111010000000000000000000000000000000000000000000000 ;
0:
09
b10000000100 8
b10000000011 7
b10000000011 6
b100000000111101000000000000000000000000000000000000000000000000 5
b11101000000000000000000000000000000000000000000000000 4
b11101000000000000000000000000000000000000000000000000 3
b10 2
b1 1
b11101000000000000000000000000000000000000000000000000 0
b10000000011 /
b11101000000000000000000000000000000000000000000000000 .
b1110100000000000000000000000000000000000000000000000 -
0,
0+
0*
0)
b1100000000100100000000000000000000000000000000000000000000000000 (
b100000001000011100000000000000000000000000000000000000000000000 '
b100000000111101000000000000000000000000000000000000000000000000 &
b100000000100100000000000000000000000000000000000000000000000000 %
b100000001000011100000000000000000000000000000000000000000000000 $
b100000000100100000000000000000000000000000000000000000000000000 #
b100000001000011100000000000000000000000000000000000000000000000 "
b100000000111101000000000000000000000000000000000000000000000000 !
$end
#10000
b1 I
b1 J
b10100000000000000000000000000000000000000000000000000 4
b1 1
b1 K
b10100000000000000000000000000000000000000000000000000 3
b10100000000000000000000000000000000000000000000000000 0
b100000000110100000000000000000000000000000000000000000000000000 !
b100000000110100000000000000000000000000000000000000000000000000 &
b100000000110100000000000000000000000000000000000000000000000000 5
1)
b10000000011 6
b10000000011 7
b10000000000000000000000000000000000000000000000000000 .
b10100000000000000000000000000000000000000000000000000 ;
b101000000000000000000000000000000000000000000000000000 -
b101000000000000000000000000000000000000000000000000000 H
b10000000001 F
0=
b11110000000000000000000000000000000000000000000000000 A
b1110000000000000000000000000000000000000000000000000 C
b1010000000000000000000000000000000000000000000000000 B
b1 2
b10000000011 <
b10000000001 /
b10000000010 8
b100000000010100000000000000000000000000000000000000000000000000 (
b1110000000000000000000000000000000000000000000000000 @
b10000000010 G
b1100000000010100000000000000000000000000000000000000000000000000 #
b1100000000010100000000000000000000000000000000000000000000000000 %
b100000000101110000000000000000000000000000000000000000000000000 "
b100000000101110000000000000000000000000000000000000000000000000 $
b100000000101110000000000000000000000000000000000000000000000000 '
#20000
b10100000000000000000000000000000000000000000000000000 4
b1 1
b1 K
b1 J
b10100000000000000000000000000000000000000000000000000 3
b10100000000000000000000000000000000000000000000000000 0
b1 I
b100000000110100000000000000000000000000000000000000000000000000 !
b100000000110100000000000000000000000000000000000000000000000000 &
b100000000110100000000000000000000000000000000000000000000000000 5
b10000000000000000000000000000000000000000000000000000 .
b10100000000000000000000000000000000000000000000000000 ;
b101000000000000000000000000000000000000000000000000000 -
b101000000000000000000000000000000000000000000000000000 H
b10000000011 6
b10000000011 7
b1110000000000000000000000000000000000000000000000000 ?
1:
b10000000010 F
b11110000000000000000000000000000000000000000000000000 A
b1110000000000000000000000000000000000000000000000000 C
b1010000000000000000000000000000000000000000000000000 B
b1 2
b10000000011 <
b10000000001 /
b10000000010 8
b100000000101110000000000000000000000000000000000000000000000000 (
b100000000000000000000000000000000000000000000000000 @
b10000000001 G
b1100000000101110000000000000000000000000000000000000000000000000 #
b1100000000101110000000000000000000000000000000000000000000000000 %
b100000000010100000000000000000000000000000000000000000000000000 "
b100000000010100000000000000000000000000000000000000000000000000 $
b100000000010100000000000000000000000000000000000000000000000000 '
#30000
b10000000001 /
b1 1
b1 K
b10000000010 <
b0 I
b1 J
b1100000000010100000000000000000000000000000000000000000000000000 !
b1100000000010100000000000000000000000000000000000000000000000000 &
b1100000000010100000000000000000000000000000000000000000000000000 5
1+
b10100000000000000000000000000000000000000000000000000 4
b10000000001 6
b10000000001 7
b10100000000000000000000000000000000000000000000000000 3
b10100000000000000000000000000000000000000000000000000 0
b10100000000000000000000000000000000000000000000000000 A
b100000000000000000000000000000000000000000000000000 C
b10100000000000000000000000000000000000000000000000000 .
b101000000000000000000000000000000000000000000000000 ;
b1010000000000000000000000000000000000000000000000000 -
b1010000000000000000000000000000000000000000000000000 H
0)
b100000000000000000000000000000000000000000000000000 ?
b10000000001 F
b10100000000000000000000000000000000000000000000000000 D
b100000000000000000000000000000000000000000000000000 E
b1010000000000000000000000000000000000000000000000000 B
b1 2
b100000000010100000000000000000000000000000000000000000000000000 (
0:
b10000000010 G
1>
b1100000000010100000000000000000000000000000000000000000000000000 #
b1100000000010100000000000000000000000000000000000000000000000000 %
b1100000000100100000000000000000000000000000000000000000000000000 "
b1100000000100100000000000000000000000000000000000000000000000000 $
b1100000000100100000000000000000000000000000000000000000000000000 '
#40000
b0 J
b1111111111 6
b1111111111 7
b1011111111110000000000000000000000000000000000000000000000000000 !
b1011111111110000000000000000000000000000000000000000000000000000 &
b1011111111110000000000000000000000000000000000000000000000000000 5
b10000000000000000000000000000000000000000000000000000 4
b10000000000000000000000000000000000000000000000000000 3
b10000000000000000000000000000000000000000000000000000 0
b0 1
b0 K
b10000000000000000000000000000000000000000000000000000 A
b0 C
b10000000000000000000000000000000000000000000000000000 .
b10000000000000000000000000000000000000000000000000000 ;
b10000000000000000000000000000000000000000000000000000 -
b10000000000000000000000000000000000000000000000000000 H
1+
0)
b0 ?
b1111111111 F
1=
b10000000000000000000000000000000000000000000000000000 D
b0 E
b0 B
b1111111111 2
b1111111111 <
b1111111111 /
b1111111111 8
b1011111111110000000000000000000000000000000000000000000000000000 (
b0 @
1:
b0 G
0>
b11111111110000000000000000000000000000000000000000000000000000 #
b11111111110000000000000000000000000000000000000000000000000000 %
b0 "
b0 $
b0 '
#50000
b11111111110000000000000000000000000000000000000000000000000000 !
b11111111110000000000000000000000000000000000000000000000000000 &
b11111111110000000000000000000000000000000000000000000000000000 5
0+
1)
0=
b11111111110000000000000000000000000000000000000000000000000000 (
b1011111111110000000000000000000000000000000000000000000000000000 #
b1011111111110000000000000000000000000000000000000000000000000000 %
#60000
b11111001111111110101110000101000111101011100001010010 4
b100000010001111001111111110101110000101000111101011100001010010 !
b100000010001111001111111110101110000101000111101011100001010010 &
b100000010001111001111111110101110000101000111101011100001010010 5
b11111001111111110101110000101000111101011100001010010 3
b11111001111111110101110000101000111101011100001010010 0
0)
b10000001000 6
b10000001000 7
b10100011110101110000101000111101011100001010001111011 D
b100011110101110000101000111101011100001010001111011 E
b11111010000000000000000000000000000000000000000000000 A
b1111010000000000000000000000000000000000000000000000 C
b11111001111111110101110000101000111101011100001010010 .
b11111001111111110101110000101000111101011100001010010 ;
b11111001111111110101110000101000111101011100001010010 -
b11111001111111110101110000101000111101011100001010010 H
b100011110101110000101000111101011100001010001111011 ?
b1111111000 F
1=
b10000001000 <
b10000001000 /
b10000001000 8
b1010001111010111000010100011110101110 B
b10000 2
b1011111110000100011110101110000101000111101011100001010001111011 (
b1111010000000000000000000000000000000000000000000000 @
0:
b10000001000 G
b11111110000100011110101110000101000111101011100001010001111011 #
b11111110000100011110101110000101000111101011100001010001111011 %
b100000010001111010000000000000000000000000000000000000000000000 "
b100000010001111010000000000000000000000000000000000000000000000 $
b100000010001111010000000000000000000000000000000000000000000000 '
#70000
b10000001001 6
b10000001001 7
b10000000111 /
b1 1
b1 K
b10000001001 <
b1 I
b11111010000000000000000000000000000000000000000000000 4
b0 J
b11111010000000000000000000000000000000000000000000000 3
b11111010000000000000000000000000000000000000000000000 0
b100000010011111010000000000000000000000000000000000000000000000 !
b100000010011111010000000000000000000000000000000000000000000000 &
b100000010011111010000000000000000000000000000000000000000000000 5
0,
b111101000000000000000000000000000000000000000000000000 .
b11111010000000000000000000000000000000000000000000000 ;
b111110100000000000000000000000000000000000000000000000 -
b111110100000000000000000000000000000000000000000000000 H
1)
b11111010000000000000000000000000000000000000000000000 D
b1111010000000000000000000000000000000000000000000000 E
b11111010000000000000000000000000000000000000000000000 B
b0 2
b1111010000000000000000000000000000000000000000000000 ?
b10000001000 F
0=
b100000010001111010000000000000000000000000000000000000000000000 (
b1100000010001111010000000000000000000000000000000000000000000000 #
b1100000010001111010000000000000000000000000000000000000000000000 %
#80000
b1 J
b11111110010100011110101110000101000111101011100001010001111011 !
b11111110010100011110101110000101000111101011100001010001111011 &
b11111110010100011110101110000101000111101011100001010001111011 5
b10100011110101110000101000111101011100001010001111011 4
b1 1
b1 K
b1111111001 6
b1111111001 7
b10100011110101110000101000111101011100001010001111011 3
b10100011110101110000101000111101011100001010001111011 0
b1 I
b10100011110101110000101000111101011100001010001111011 A
b100011110101110000101000111101011100001010001111011 C
b1111111001 <
b1111110111 /
b1111111000 8
b10001111010111000010100011110101110000101000111101100 .
b10100011110101110000101000111101011100001010001111011 ;
b101000111101011100001010001111010111000010100011110110 -
b101000111101011100001010001111010111000010100011110110 H
b100011110101110000101000111101011100001010001111011 ?
b1111111000 F
b10100011110101110000101000111101011100001010001111011 D
b100011110101110000101000111101011100001010001111011 E
b10100011110101110000101000111101011100001010001111011 B
b0 2
b11111110000100011110101110000101000111101011100001010001111011 (
b100011110101110000101000111101011100001010001111011 @
0:
b1111111000 G
b1011111110000100011110101110000101000111101011100001010001111011 #
b1011111110000100011110101110000101000111101011100001010001111011 %
b11111110000100011110101110000101000111101011100001010001111011 "
b11111110000100011110101110000101000111101011100001010001111011 $
b11111110000100011110101110000101000111101011100001010001111011 '
#90000
b0 1
b0 K
b11000000000000000000000000000000000000000000000000000 4
b0 J
b11000000000000000000000000000000000000000000000000000 3
b11000000000000000000000000000000000000000000000000000 0
b1 I
b100000000001000000000000000000000000000000000000000000000000000 !
b100000000001000000000000000000000000000000000000000000000000000 &
b100000000001000000000000000000000000000000000000000000000000000 5
0)
b10000000000 6
b10000000000 7
b11100000000000000000000000000000000000000000000000000 D
b1100000000000000000000000000000000000000000000000000 E
b111000000000000000000000000000000000000000000000000000 .
b111000000000000000000000000000000000000000000000000000 ;
b111000000000000000000000000000000000000000000000000000 -
b111000000000000000000000000000000000000000000000000000 H
b1100000000000000000000000000000000000000000000000000 ?
b10000000000 F
1=
b10100000000000000000000000000000000000000000000000000 A
b100000000000000000000000000000000000000000000000000 C
b11100000000000000000000000000000000000000000000000000 B
b0 2
b10000000001 <
b10000000000 /
b10000000000 8
b1100000000001100000000000000000000000000000000000000000000000000 (
b100000000000000000000000000000000000000000000000000 @
b10000000000 G
b100000000001100000000000000000000000000000000000000000000000000 #
b100000000001100000000000000000000000000000000000000000000000000 %
b100000000000100000000000000000000000000000000000000000000000000 "
b100000000000100000000000000000000000000000000000000000000000000 $
b100000000000100000000000000000000000000000000000000000000000000 '
