Hazards/Data_Hazards/hazard_detection_unit.v
module hazard_detection_unit (
    input [5:0] rs1_IF_ID,
    input [5:0] rs2_IF_ID,
    input [5:0] rd_ID_EX,
    input mem_read_ID_EX,
    input clk,
    input rst,
    output reg stall
);

  reg reg_eq_A;
  reg reg_eq_B;
  reg to_stall;
  reg curr_stage;

  always @(posedge clk) begin
    if (rst) begin
      stall <= 1'b0;
    end else begin
      stall <= to_stall;
      curr_stage <= to_stall;
    end
  end

  always @(*) begin
    reg_eq_A = (rd_ID_EX == rs1_IF_ID);
    reg_eq_B = (rd_ID_EX == rs2_IF_ID);

    to_stall = (curr_stage) ? (1'b0) : ( (mem_read_ID_EX) ? (((reg_eq_A) | (reg_eq_B)) ? (1'b1) : (1'b0)) : (1'b0));
  end

endmodule

Hazards/Data_Hazards/tb.v
`timescale 1ns / 1ps

module hazard_detection_unit_tb;

  // Testbench signals
  reg [5:0] rs1_IF_ID;
  reg [5:0] rs2_IF_ID;
  reg [5:0] rd_ID_EX;
  reg mem_read_ID_EX;
  reg clk;
  reg rst;
  wire stall;

  // Instantiate the Unit Under Test (UUT)
  hazard_detection_unit uut (
      .rs1_IF_ID(rs1_IF_ID),
      .rs2_IF_ID(rs2_IF_ID),
      .rd_ID_EX(rd_ID_EX),
      .mem_read_ID_EX(mem_read_ID_EX),
      .clk(clk),
      .rst(rst),
      .stall(stall)
  );
  wire curr_state = uut.curr_stage;
  // Clock generation
  initial begin
    clk = 0;
    forever #5 clk = ~clk;  // 10ns period, 100MHz clock
  end

  // Test stimulus
  initial begin
    // Initialize waveform dump (for viewing in simulation)
    $dumpfile("hazard_detection_unit_tb.vcd");
    $dumpvars(0, hazard_detection_unit_tb);

    // Monitor output
    $monitor("Time=%0t | rst=%b | mem_read=%b | rd=%h | rs1=%h | rs2=%h | stall=%b", $time, rst,
             mem_read_ID_EX, rd_ID_EX, rs1_IF_ID, rs2_IF_ID, stall);

    // Initialize all inputs
    rst = 1;
    mem_read_ID_EX = 0;
    rd_ID_EX = 6'b000000;
    rs1_IF_ID = 6'b000000;
    rs2_IF_ID = 6'b000000;

    // Apply reset
    #20;
    rst = 0;
    #10;

    // ============================================
    // Test Case 1: No hazard (no mem_read)
    // ============================================
    $display("\n=== Test Case 1: No Hazard (mem_read=0) ===");
    mem_read_ID_EX = 0;
    rd_ID_EX = 6'b000001;
    rs1_IF_ID = 6'b000001;
    rs2_IF_ID = 6'b000010;
    #20;  // INSERT YOUR OWN VALUES HERE

    // ============================================
    // Test Case 2: RAW hazard on rs1 with load
    // ============================================
    $display("\n=== Test Case 2: RAW Hazard on rs1 ===");
    mem_read_ID_EX = 1;
    rd_ID_EX = 6'b000101;
    rs1_IF_ID = 6'b000101;  // Matches rd_ID_EX
    rs2_IF_ID = 6'b000010;
    #40;  // INSERT YOUR OWN VALUES HERE

    // ============================================
    // Test Case 3: RAW hazard on rs2 with load
    // ============================================
    $display("\n=== Test Case 3: RAW Hazard on rs2 ===");
    mem_read_ID_EX = 1;
    rd_ID_EX = 6'b001010;
    rs1_IF_ID = 6'b000001;
    rs2_IF_ID = 6'b001010;  // Matches rd_ID_EX
    #40;  // INSERT YOUR OWN VALUES HERE

    // ============================================
    // Test Case 4: RAW hazard on both rs1 and rs2
    // ============================================
    $display("\n=== Test Case 4: RAW Hazard on Both rs1 and rs2 ===");
    mem_read_ID_EX = 1;
    rd_ID_EX = 6'b001111;
    rs1_IF_ID = 6'b001111;  // Matches rd_ID_EX
    rs2_IF_ID = 6'b001111;  // Also matches rd_ID_EX
    #40;  // INSERT YOUR OWN VALUES HERE

    // ============================================
    // Test Case 5: No hazard (different registers)
    // ============================================
    $display("\n=== Test Case 5: No Hazard (Different Registers) ===");
    mem_read_ID_EX = 0;
    rd_ID_EX = 6'b010101;
    rs1_IF_ID = 6'b010101;
    rs2_IF_ID = 6'b000010;
    #20;  // INSERT YOUR OWN VALUES HERE

    // // =================i===========================
    // // Test Case 6: INSERT YOUR OWN TEST CASE
    // // ============================================
    // $display("\n=== Test Case 6: Custom Test ===");
    // mem_read_ID_EX = /* INSERT VALUE */;
    // rd_ID_EX = /* INSERT VALUE */;
    // rs1_IF_ID = /* INSERT VALUE */;
    // rs2_IF_ID = /* INSERT VALUE */;
    // #20;
    //
    // // ============================================
    // // Test Case 7: INSERT YOUR OWN TEST CASE
    // // ============================================
    // $display("\n=== Test Case 7: Custom Test ===");
    // mem_read_ID_EX = /* INSERT VALUE */;
    // rd_ID_EX = /* INSERT VALUE */;
    // rs1_IF_ID = /* INSERT VALUE */;
    // rs2_IF_ID = /* INSERT VALUE */;
    // #20;
    //
    // // ============================================
    // // Test Case 8: INSERT YOUR OWN TEST CASE
    // // ============================================
    // $display("\n=== Test Case 8: Custom Test ===");
    // mem_read_ID_EX = /* INSERT VALUE */;
    // rd_ID_EX = /* INSERT VALUE */;
    // rs1_IF_ID = /* INSERT VALUE */;
    // rs2_IF_ID = /* INSERT VALUE */;
    // #20;
    //
    // // ============================================
    // // Reset test
    // // ============================================
    // $display("\n=== Reset Test ===");
    // rst = 1;
    // #20;
    // rst = 0;
    // #20;
    //
    // End simulation
    $display("\n=== Simulation Complete ===");
    $finish;
  end

endmodule

Hazards/Data_Hazards/hazard_detection_unit_tb.vcd
$date
	Mon Nov  3 23:28:24 2025
$end
$version
	Icarus Verilog
$end
$timescale
	1ps
$end
$scope module hazard_detection_unit_tb $end
$var wire 1 ! curr_state $end
$var wire 1 " stall $end
$var reg 1 # clk $end
$var reg 1 $ mem_read_ID_EX $end
$var reg 6 % rd_ID_EX [5:0] $end
$var reg 6 & rs1_IF_ID [5:0] $end
$var reg 6 ' rs2_IF_ID [5:0] $end
$var reg 1 ( rst $end
$scope module uut $end
$var wire 1 # clk $end
$var wire 1 $ mem_read_ID_EX $end
$var wire 6 ) rd_ID_EX [5:0] $end
$var wire 6 * rs1_IF_ID [5:0] $end
$var wire 6 + rs2_IF_ID [5:0] $end
$var wire 1 ( rst $end
$var reg 1 , curr_stage $end
$var reg 1 - reg_eq_A $end
$var reg 1 . reg_eq_B $end
$var reg 1 " stall $end
$var reg 1 / to_stall $end
$upscope $end
$upscope $end
$enddefinitions $end
$comment Show the parameter values. $end
$dumpall
$end
#0
$dumpvars
0/
1.
1-
x,
b0 +
b0 *
b0 )
1(
b0 '
b0 &
b0 %
0$
0#
x"
x!
$end
#5000
0"
1#
#10000
0#
#15000
1#
#20000
0#
0(
#25000
0!
0,
1#
#30000
0.
0#
b10 '
b10 +
b1 &
b1 *
b1 %
b1 )
#35000
1#
#40000
0#
#45000
1#
#50000
1/
0#
b101 &
b101 *
b101 %
b101 )
1$
#55000
0/
1!
1,
1"
1#
#60000
0#
#65000
1/
0!
0,
0"
1#
#70000
0#
#75000
0/
1!
1,
1"
1#
#80000
0#
#85000
1/
0!
0,
0"
1#
#90000
1.
0-
0#
b1010 '
b1010 +
b1 &
b1 *
b1010 %
b1010 )
#95000
0/
1!
1,
1"
1#
#100000
0#
#105000
1/
0!
0,
0"
1#
#110000
0#
#115000
0/
1!
1,
1"
1#
#120000
0#
#125000
1/
0!
0,
0"
1#
#130000
1-
0#
b1111 '
b1111 +
b1111 &
b1111 *
b1111 %
b1111 )
#135000
0/
1!
1,
1"
1#
#140000
0#
#145000
1/
0!
0,
0"
1#
#150000
0#
#155000
0/
1!
1,
1"
1#
#160000
0#
#165000
1/
0!
0,
0"
1#
#170000
0/
0.
0#
b10 '
b10 +
b10101 &
b10101 *
b10101 %
b10101 )
0$
